[
  {
    "id": "cmqetm32n0002g37k15z035s4",
    "title": "European Advanced Materials Congress 2025",
    "date": "30 March – 01 April 2026",
    "location": "Stockholm, Sweden",
    "image": "",
    "link": "#",
    "eventType": "upcoming",
    "order": 0,
    "createdAt": "2026-06-15T06:16:56.592Z",
    "updatedAt": "2026-06-15T06:16:56.592Z"
  },
  {
    "id": "cmqetm32r0003g37kvsagt475",
    "title": "International Robotics Summit 2025",
    "date": "15-17 June 2025",
    "location": "Tokyo, Japan",
    "image": "",
    "link": "#",
    "eventType": "upcoming",
    "order": 1,
    "createdAt": "2026-06-15T06:16:56.595Z",
    "updatedAt": "2026-06-15T06:16:56.595Z"
  },
  {
    "id": "cmqetm32s0004g37kgath9ay9",
    "title": "Global Health Innovations Forum 2025",
    "date": "10-12 September 2025",
    "location": "San Francisco, USA",
    "image": "",
    "link": "#",
    "eventType": "upcoming",
    "order": 2,
    "createdAt": "2026-06-15T06:16:56.597Z",
    "updatedAt": "2026-06-15T06:16:56.597Z"
  },
  {
    "id": "cmqetm32u0005g37k9a7cj39b",
    "title": "Sustainable Energy Conference 2025",
    "date": "05-07 November 2025",
    "location": "Amsterdam, Netherlands",
    "image": "",
    "link": "#",
    "eventType": "upcoming",
    "order": 3,
    "createdAt": "2026-06-15T06:16:56.598Z",
    "updatedAt": "2026-06-15T06:16:56.598Z"
  },
  {
    "id": "cmqetm32v0006g37kyk59u22t",
    "title": "Artificial Intelligence in Healthcare Summit 2025",
    "date": "20-22 January 2026",
    "location": "Toronto, Canada",
    "image": "",
    "link": "#",
    "eventType": "upcoming",
    "order": 4,
    "createdAt": "2026-06-15T06:16:56.600Z",
    "updatedAt": "2026-06-15T06:16:56.600Z"
  },
  {
    "id": "cmqetm32x0007g37kmzyawo33",
    "title": "European Advanced Materials Congress 2025",
    "date": "30 March – 01 April 2026",
    "location": "Stockholm, Sweden",
    "image": "",
    "link": "#",
    "eventType": "archive",
    "order": 0,
    "createdAt": "2026-06-15T06:16:56.601Z",
    "updatedAt": "2026-06-15T06:16:56.601Z"
  },
  {
    "id": "cmqetm32y0008g37kn5jvwrx5",
    "title": "International Robotics Summit 2025",
    "date": "15-17 June 2025",
    "location": "Tokyo, Japan",
    "image": "",
    "link": "#",
    "eventType": "archive",
    "order": 1,
    "createdAt": "2026-06-15T06:16:56.603Z",
    "updatedAt": "2026-06-15T06:16:56.603Z"
  },
  {
    "id": "cmqetm3300009g37kveeequ8y",
    "title": "Global Health Innovations Forum 2025",
    "date": "10-12 September 2025",
    "location": "San Francisco, USA",
    "image": "",
    "link": "#",
    "eventType": "archive",
    "order": 2,
    "createdAt": "2026-06-15T06:16:56.604Z",
    "updatedAt": "2026-06-15T06:16:56.604Z"
  },
  {
    "id": "cmqetm331000ag37k49afkcxm",
    "title": "Sustainable Energy Conference 2025",
    "date": "05-07 November 2025",
    "location": "Amsterdam, Netherlands",
    "image": "",
    "link": "#",
    "eventType": "archive",
    "order": 3,
    "createdAt": "2026-06-15T06:16:56.606Z",
    "updatedAt": "2026-06-15T06:16:56.606Z"
  },
  {
    "id": "cmqetm333000bg37kao8wbrni",
    "title": "Artificial Intelligence in Healthcare Summit 2025",
    "date": "20-22 January 2026",
    "location": "Toronto, Canada",
    "image": "",
    "link": "#",
    "eventType": "archive",
    "order": 4,
    "createdAt": "2026-06-15T06:16:56.607Z",
    "updatedAt": "2026-06-15T06:16:56.607Z"
  },
  {
    "id": "cmqeto43h000apjhbw4ljt3sh",
    "title": "European Advanced Materials Congress 2025",
    "date": "30 March – 01 April 2026",
    "location": "Stockholm, Sweden",
    "image": "",
    "link": "#",
    "eventType": "upcoming",
    "order": 0,
    "createdAt": "2026-06-15T06:18:31.229Z",
    "updatedAt": "2026-06-15T06:18:31.229Z"
  },
  {
    "id": "cmqeto43i000bpjhb640012go",
    "title": "International Robotics Summit 2025",
    "date": "15-17 June 2025",
    "location": "Tokyo, Japan",
    "image": "",
    "link": "#",
    "eventType": "upcoming",
    "order": 1,
    "createdAt": "2026-06-15T06:18:31.231Z",
    "updatedAt": "2026-06-15T06:18:31.231Z"
  },
  {
    "id": "cmqeto43j000cpjhbiliq83eg",
    "title": "Global Health Innovations Forum 2025",
    "date": "10-12 September 2025",
    "location": "San Francisco, USA",
    "image": "",
    "link": "#",
    "eventType": "upcoming",
    "order": 2,
    "createdAt": "2026-06-15T06:18:31.232Z",
    "updatedAt": "2026-06-15T06:18:31.232Z"
  },
  {
    "id": "cmqeto43l000dpjhbqy77kgkr",
    "title": "Sustainable Energy Conference 2025",
    "date": "05-07 November 2025",
    "location": "Amsterdam, Netherlands",
    "image": "",
    "link": "#",
    "eventType": "upcoming",
    "order": 3,
    "createdAt": "2026-06-15T06:18:31.233Z",
    "updatedAt": "2026-06-15T06:18:31.233Z"
  },
  {
    "id": "cmqeto43m000epjhb0ibybx7k",
    "title": "Artificial Intelligence in Healthcare Summit 2025",
    "date": "20-22 January 2026",
    "location": "Toronto, Canada",
    "image": "",
    "link": "#",
    "eventType": "upcoming",
    "order": 4,
    "createdAt": "2026-06-15T06:18:31.235Z",
    "updatedAt": "2026-06-15T06:18:31.235Z"
  },
  {
    "id": "cmqeto43o000fpjhbwk5fm6or",
    "title": "European Advanced Materials Congress 2025",
    "date": "30 March – 01 April 2026",
    "location": "Stockholm, Sweden",
    "image": "",
    "link": "#",
    "eventType": "archive",
    "order": 0,
    "createdAt": "2026-06-15T06:18:31.236Z",
    "updatedAt": "2026-06-15T06:18:31.236Z"
  },
  {
    "id": "cmqeto43p000gpjhbjsvq2smi",
    "title": "International Robotics Summit 2025",
    "date": "15-17 June 2025",
    "location": "Tokyo, Japan",
    "image": "",
    "link": "#",
    "eventType": "archive",
    "order": 1,
    "createdAt": "2026-06-15T06:18:31.237Z",
    "updatedAt": "2026-06-15T06:18:31.237Z"
  },
  {
    "id": "cmqeto43q000hpjhbhk1tvaj3",
    "title": "Global Health Innovations Forum 2025",
    "date": "10-12 September 2025",
    "location": "San Francisco, USA",
    "image": "",
    "link": "#",
    "eventType": "archive",
    "order": 2,
    "createdAt": "2026-06-15T06:18:31.238Z",
    "updatedAt": "2026-06-15T06:18:31.238Z"
  },
  {
    "id": "cmqeto43r000ipjhb6k39opa2",
    "title": "Sustainable Energy Conference 2025",
    "date": "05-07 November 2025",
    "location": "Amsterdam, Netherlands",
    "image": "",
    "link": "#",
    "eventType": "archive",
    "order": 3,
    "createdAt": "2026-06-15T06:18:31.240Z",
    "updatedAt": "2026-06-15T06:18:31.240Z"
  },
  {
    "id": "cmqeto43t000jpjhbzf8w3rxx",
    "title": "Artificial Intelligence in Healthcare Summit 2025",
    "date": "20-22 January 2026",
    "location": "Toronto, Canada",
    "image": "",
    "link": "#",
    "eventType": "archive",
    "order": 4,
    "createdAt": "2026-06-15T06:18:31.241Z",
    "updatedAt": "2026-06-15T06:18:31.241Z"
  },
  {
    "id": "cmqev7u0z00008tj362z83dbf",
    "title": "European Advanced Materials Congress 2025",
    "date": "30 March – 01 April 2026",
    "location": "Stockholm, Sweden",
    "image": "",
    "link": "#",
    "eventType": "individual",
    "order": 0,
    "createdAt": "2026-06-15T07:01:50.916Z",
    "updatedAt": "2026-06-15T07:01:50.916Z"
  },
  {
    "id": "cmqev7u1500018tj3n2i6a3ku",
    "title": "International Robotics Summit 2025",
    "date": "15-17 June 2025",
    "location": "Tokyo, Japan",
    "image": "",
    "link": "#",
    "eventType": "individual",
    "order": 1,
    "createdAt": "2026-06-15T07:01:50.922Z",
    "updatedAt": "2026-06-15T07:01:50.922Z"
  },
  {
    "id": "cmqev7u1700028tj3l6ii9byo",
    "title": "Global Health Innovations Forum 2025",
    "date": "10-12 September 2025",
    "location": "San Francisco, USA",
    "image": "",
    "link": "#",
    "eventType": "individual",
    "order": 2,
    "createdAt": "2026-06-15T07:01:50.924Z",
    "updatedAt": "2026-06-15T07:01:50.924Z"
  },
  {
    "id": "cmqev7u1900038tj3rof70fo3",
    "title": "Sustainable Energy Conference 2025",
    "date": "05-07 November 2025",
    "location": "Amsterdam, Netherlands",
    "image": "",
    "link": "#",
    "eventType": "individual",
    "order": 3,
    "createdAt": "2026-06-15T07:01:50.926Z",
    "updatedAt": "2026-06-15T07:01:50.926Z"
  },
  {
    "id": "cmqev7u1b00048tj3degon3el",
    "title": "Artificial Intelligence in Healthcare Summit 2025",
    "date": "20-22 January 2026",
    "location": "Toronto, Canada",
    "image": "",
    "link": "#",
    "eventType": "individual",
    "order": 4,
    "createdAt": "2026-06-15T07:01:50.928Z",
    "updatedAt": "2026-06-15T07:01:50.928Z"
  }
]